.coveragerc
.editorconfig
.travis.yml
CHANGES.rst
CONTRIBUTORS.rst
DEVELOP.rst
LICENSE.GPL
LICENSE.rst
MANIFEST.in
README.rst
base.cfg
bobtemplate.cfg
buildout.cfg
constraints.txt
constraints_plone43.txt
constraints_plone50.txt
constraints_plone51.txt
constraints_plone52.txt
requirements.txt
setup.cfg
setup.py
test_plone43.cfg
test_plone50.cfg
test_plone51.cfg
test_plone52.cfg
tox.ini
docs/conf.py
docs/index.rst
src/collective/__init__.py
src/collective.debug.egg-info/PKG-INFO
src/collective.debug.egg-info/SOURCES.txt
src/collective.debug.egg-info/dependency_links.txt
src/collective.debug.egg-info/entry_points.txt
src/collective.debug.egg-info/namespace_packages.txt
src/collective.debug.egg-info/not-zip-safe
src/collective.debug.egg-info/requires.txt
src/collective.debug.egg-info/top_level.txt
src/collective/debug/__init__.py
src/collective/debug/configure.zcml
src/collective/debug/interfaces.py
src/collective/debug/permissions.zcml
src/collective/debug/setuphandlers.py
src/collective/debug/testing.py
src/collective/debug/browser/__init__.py
src/collective/debug/browser/configure.zcml
src/collective/debug/browser/configure2.zcml
src/collective/debug/browser/debug.pt
src/collective/debug/browser/debug.py
src/collective/debug/browser/overrides/.gitkeep
src/collective/debug/browser/static/.gitkeep
src/collective/debug/locales/README.rst
src/collective/debug/locales/__init__.py
src/collective/debug/locales/collective.debug.pot
src/collective/debug/locales/update.py
src/collective/debug/locales/update.sh
src/collective/debug/locales/en/LC_MESSAGES/collective.debug.mo
src/collective/debug/locales/en/LC_MESSAGES/collective.debug.po
src/collective/debug/profiles/default/browserlayer.xml
src/collective/debug/profiles/default/catalog.xml
src/collective/debug/profiles/default/metadata.xml
src/collective/debug/profiles/default/rolemap.xml
src/collective/debug/profiles/default/registry/main.xml
src/collective/debug/profiles/uninstall/browserlayer.xml
src/collective/debug/tests/__init__.py
src/collective/debug/tests/test_robot.py
src/collective/debug/tests/test_setup.py
src/collective/debug/tests/robot/test_example.robot