Metadata-Version: 2.1
Name: collective.debug
Version: 1.0a2
Summary: A Plone debug view for introspecting the current context, user, roles and instance dict
Home-page: https://github.com/collective/collective.debug
Author: Andreas Jung
Author-email: info@zopyx.com
License: GPL version 2
Project-URL: PyPI, https://pypi.python.org/pypi/collective.debug
Project-URL: Source, https://github.com/collective/collective.debug
Project-URL: Tracker, https://github.com/collective/collective.debug/issues
Keywords: Python Plone CMS
Platform: UNKNOWN
Classifier: Environment :: Web Environment
Classifier: Framework :: Plone
Classifier: Framework :: Plone :: Addon
Classifier: Framework :: Plone :: 4.3
Classifier: Framework :: Plone :: 5.0
Classifier: Framework :: Plone :: 5.1
Classifier: Framework :: Plone :: 5.2
Classifier: Programming Language :: Python
Classifier: Programming Language :: Python :: 2.7
Classifier: Programming Language :: Python :: 3.7
Classifier: Programming Language :: Python :: 3.8
Classifier: Operating System :: OS Independent
Classifier: License :: OSI Approved :: GNU General Public License v2 (GPLv2)
Requires-Python: ==2.7, >=3.7
Provides-Extra: test
